ptrack/__init__.py
ptrack/apps.py
ptrack/encoder.py
ptrack/exceptions.py
ptrack/trackers.py
ptrack/urls.py
ptrack/views.py
ptrack/templatetags/__init__.py
ptrack/templatetags/ptrack.py
test_ptrack/__init__.py
test_ptrack/settings.py
test_ptrack/test_encoder.py
test_ptrack/test_trackers.py
test_ptrack/test_views.py
django_ptrack-3.0.0.dist-info/LICENSE.txt
django_ptrack-3.0.0.dist-info/METADATA
django_ptrack-3.0.0.dist-info/WHEEL
django_ptrack-3.0.0.dist-info/top_level.txt
django_ptrack-3.0.0.dist-info/RECORD
