Metadata-Version: 2.1
Name: django-ptrack
Version: 3.0.0
Summary: Ptrack is a tracking pixel library for Django
Home-page: https://github.com/indeedeng/django-ptrack
Author: Richard Latimer, Sarah Ellis
Author-email: rlatimer@indeed.com, sellis@indeed.com
License: Apache
Keywords: django
Platform: UNKNOWN
Classifier: Development Status :: 5 - Production/Stable
Classifier: Intended Audience :: Developers
Classifier: Environment :: Web Environment
Classifier: Framework :: Django
Classifier: Framework :: Django :: 2.0
Classifier: License :: OSI Approved :: Apache Software License
Classifier: Programming Language :: Python :: 3
Classifier: Programming Language :: Python :: 3.6
License-File: LICENSE.txt
Requires-Dist: Django (>=2.0.0)
Requires-Dist: pynacl (>=1.0.1)
Provides-Extra: legacy
Requires-Dist: pycrypto (>=2.6.1) ; extra == 'legacy'
